sigopt_sklearn/__init__.py
sigopt_sklearn/ensemble.py
sigopt_sklearn/search.py
sigopt_sklearn/sklearn_fit.py
sigopt_sklearn/version.py
sigopt_sklearn-2.2.0.dist-info/LICENSE
sigopt_sklearn-2.2.0.dist-info/METADATA
sigopt_sklearn-2.2.0.dist-info/WHEEL
sigopt_sklearn-2.2.0.dist-info/top_level.txt
sigopt_sklearn-2.2.0.dist-info/RECORD
