Metadata-Version: 2.1
Name: sigopt-sklearn
Version: 2.2.0
Summary: SigOpt + scikit-learn Integrations
Home-page: https://sigopt.com/
Author: SigOpt
Author-email: support@sigopt.com
License: UNKNOWN
Platform: UNKNOWN
Classifier: Development Status :: 3 - Alpha
Classifier: Intended Audience :: Developers
Classifier: License :: OSI Approved :: MIT License
Classifier: Operating System :: OS Independent
Classifier: Programming Language :: Python
Classifier: Topic :: Software Development :: Libraries :: Python Modules
Requires-Dist: joblib (>=0.9.4)
Requires-Dist: numpy (>=1.9)
Requires-Dist: scikit-learn (<0.21,>=0.19)
Requires-Dist: sigopt (>=2.6.0)
Provides-Extra: ensemble
Requires-Dist: xgboost (<0.90,>=0.4a30) ; extra == 'ensemble'
